{
  "type": "minecraft:crafting_shapeless",
  "category": "misc",
  "ingredients": [
    {
      "item": "undeadremains:metatorbernite"
    },
    {
      "item": "undeadremains:metatorbernite"
    },
    {
      "item": "undeadremains:metatorbernite"
    },
    {
      "item": "undeadremains:metatorbernite"
    },
    {
      "item": "undeadremains:metatorbernite"
    },
    {
      "item": "undeadremains:metatorbernite"
    },
    {
      "item": "undeadremains:metatorbernite"
    },
    {
      "item": "undeadremains:metatorbernite"
    },
    {
      "item": "undeadremains:metatorbernite"
    }
  ],
  "result": {
    "item": "undeadremains:metatorbernite_block"
  }
}